svg/__init__.py
svg/canvas.py
svg/example.py
svg/link.py
svg/main.py
svg/server.py
svg/shapes.py
svg/style.py
svg/templates.py
python_svg-0.1.1.dist-info/METADATA
python_svg-0.1.1.dist-info/WHEEL
python_svg-0.1.1.dist-info/top_level.txt
python_svg-0.1.1.dist-info/RECORD
